<?xml version="1.0" encoding="UTF-8"?><record_update table="sys_security_acl_role">
    <sys_security_acl_role action="DELETE">
        <sys_class_name>sys_security_acl_role</sys_class_name>
        <sys_created_by>Brandon.hernandez</sys_created_by>
        <sys_created_on>2020-05-03 00:22:29</sys_created_on>
        <sys_id>e082c121db2c941058d02095ca9619fe</sys_id>
        <sys_mod_count>0</sys_mod_count>
        <sys_name>x_snc_first_respon_associate_data_lookup_table.x_snc_first_respon.associate_data_lookup_table_user</sys_name>
        <sys_package display_value="First Responder Locator" source="x_snc_first_respon">55df8b45dbec541058d02095ca961922</sys_package>
        <sys_policy/>
        <sys_scope display_value="First Responder Locator">55df8b45dbec541058d02095ca961922</sys_scope>
        <sys_security_acl display_value="x_snc_first_respon_associate_data_lookup_table">e482c121db2c941058d02095ca9619fa</sys_security_acl>
        <sys_update_name>sys_security_acl_role_e082c121db2c941058d02095ca9619fe</sys_update_name>
        <sys_updated_by>Brandon.hernandez</sys_updated_by>
        <sys_updated_on>2020-05-03 00:22:29</sys_updated_on>
        <sys_user_role display_value="x_snc_first_respon.associate_data_lookup_table_user" name="x_snc_first_respon.associate_data_lookup_table_user">db72c121db2c941058d02095ca96194a</sys_user_role>
        <transaction_id/>
    </sys_security_acl_role>
    <sys_update_version action="INSERT_OR_UPDATE">
        <action>DELETE</action>
        <application display_value="First Responder Locator">55df8b45dbec541058d02095ca961922</application>
        <file_path/>
        <instance_id>095376a56f4cd640f51e7b2f5d3ee443</instance_id>
        <instance_name>hackathon116</instance_name>
        <name>sys_security_acl_role_e082c121db2c941058d02095ca9619fe</name>
        <payload><![CDATA[<?xml version="1.0" encoding="UTF-8"?><record_update table="sys_security_acl_role"><sys_security_acl_role action="INSERT_OR_UPDATE"><sys_class_name>sys_security_acl_role</sys_class_name><sys_created_by>Brandon.hernandez</sys_created_by><sys_created_on>2020-05-03 00:22:29</sys_created_on><sys_id>e082c121db2c941058d02095ca9619fe</sys_id><sys_mod_count>0</sys_mod_count><sys_name>x_snc_first_respon_associate_data_lookup_table.x_snc_first_respon.associate_data_lookup_table_user</sys_name><sys_package display_value="First Responder Locator" source="x_snc_first_respon">55df8b45dbec541058d02095ca961922</sys_package><sys_policy/><sys_scope display_value="First Responder Locator">55df8b45dbec541058d02095ca961922</sys_scope><sys_security_acl display_value="x_snc_first_respon_associate_data_lookup_table">e482c121db2c941058d02095ca9619fa</sys_security_acl><sys_update_name>sys_security_acl_role_e082c121db2c941058d02095ca9619fe</sys_update_name><sys_updated_by>Brandon.hernandez</sys_updated_by><sys_updated_on>2020-05-03 00:22:29</sys_updated_on><sys_user_role display_value="x_snc_first_respon.associate_data_lookup_table_user" name="x_snc_first_respon.associate_data_lookup_table_user">db72c121db2c941058d02095ca96194a</sys_user_role><transaction_id/></sys_security_acl_role></record_update>]]></payload>
        <payload_hash>-1853639896</payload_hash>
        <record_name>x_snc_first_respon_associate_data_lookup_table.x_snc_first_respon.associate_data_lookup_table_user</record_name>
        <reverted_from/>
        <source>d5df8b45dbec541058d02095ca961924</source>
        <source_table>sys_update_set</source_table>
        <state>previous</state>
        <sys_created_by>Brandon.hernandez</sys_created_by>
        <sys_created_on>2020-05-03 00:22:29</sys_created_on>
        <sys_id>e0820521db2c941058d02095ca961901</sys_id>
        <sys_mod_count>0</sys_mod_count>
        <sys_recorded_at>171d7e9b2c40000001</sys_recorded_at>
        <sys_updated_by>Brandon.hernandez</sys_updated_by>
        <sys_updated_on>2020-05-03 00:22:29</sys_updated_on>
        <type>Access Roles</type>
        <update_guid>2c820521032c941076ed4d20e070cf00</update_guid>
        <update_guid_history>2c820521032c941076ed4d20e070cf00:-1853639896</update_guid_history>
    </sys_update_version>
    <sys_metadata_delete action="INSERT_OR_UPDATE">
        <sys_audit_delete display_value="x_snc_first_respon_associate_data_lookup_table.x_snc_first_respon.associate_data">d9f80565db2c941058d02095ca9619bb</sys_audit_delete>
        <sys_class_name>sys_metadata_delete</sys_class_name>
        <sys_created_by>Brandon.hernandez</sys_created_by>
        <sys_created_on>2020-05-03 00:50:39</sys_created_on>
        <sys_db_object display_value="" name="sys_security_acl_role">sys_security_acl_role</sys_db_object>
        <sys_id>a3e8b20c073d4150bf9f11543fabf2e4</sys_id>
        <sys_metadata>e082c121db2c941058d02095ca9619fe</sys_metadata>
        <sys_mod_count>0</sys_mod_count>
        <sys_name>x_snc_first_respon_associate_data_lookup_table.x_snc_first_respon.associate_data_lookup_table_user</sys_name>
        <sys_package display_value="First Responder Locator" source="x_snc_first_respon">55df8b45dbec541058d02095ca961922</sys_package>
        <sys_parent display_value="">e482c121db2c941058d02095ca9619fa</sys_parent>
        <sys_policy/>
        <sys_scope display_value="First Responder Locator">55df8b45dbec541058d02095ca961922</sys_scope>
        <sys_scope_delete display_value="">d798e2814a3448679a18a6bb4eabd319</sys_scope_delete>
        <sys_update_name>sys_security_acl_role_e082c121db2c941058d02095ca9619fe</sys_update_name>
        <sys_update_version display_value="sys_security_acl_role_e082c121db2c941058d02095ca9619fe">e0820521db2c941058d02095ca961901</sys_update_version>
        <sys_updated_by>Brandon.hernandez</sys_updated_by>
        <sys_updated_on>2020-05-03 00:50:39</sys_updated_on>
    </sys_metadata_delete>
</record_update>
